{
  "innerspeaker": {
    "current": 26.9,
    "history": [
      {
        "date": "2026-06-24 06:53:38",
        "price": 26.9
      }
    ]
  },
  "boarding house reach": {
    "current": 35.97,
    "history": [
      {
        "date": "2026-06-24 07:04:13",
        "price": 35.97
      }
    ]
  },
  "fear of the dawn": {
    "current": 37.72,
    "history": [
      {
        "date": "2026-06-24 07:04:13",
        "price": 37.72
      }
    ]
  },
  "cosa faremo da grandi": {
    "current": 25.48,
    "history": [
      {
        "date": "2026-06-24 06:53:38",
        "price": 25.48
      }
    ]
  },
  "relax": {
    "current": 29.99,
    "history": [
      {
        "date": "2026-06-24 07:04:13",
        "price": 29.99
      }
    ]
  },
  "resta vile maschio dove vai": {
    "current": 38.0,
    "history": [
      {
        "date": "2026-06-24 07:04:13",
        "price": 38.0
      }
    ]
  },
  "disco x 180 gr": {
    "current": 29.9,
    "history": [
      {
        "date": "2026-06-24 06:53:38",
        "price": 29.9
      }
    ]
  },
  "fear of music": {
    "current": 34.89,
    "history": [
      {
        "date": "2026-06-24 07:04:13",
        "price": 34.89
      }
    ]
  },
  "remain in light": {
    "current": 25.9,
    "history": [
      {
        "date": "2026-06-24 07:04:13",
        "price": 25.9
      }
    ]
  },
  "follow the leader": {
    "current": 20.27,
    "history": [
      {
        "date": "2026-06-24 06:53:38",
        "price": 20.27
      }
    ]
  },
  "up": {
    "current": 44.99,
    "history": [
      {
        "date": "2026-06-24 07:04:13",
        "price": 44.99
      }
    ]
  },
  "blood sugar sex magik": {
    "current": 31.3,
    "history": [
      {
        "date": "2026-06-24 07:04:13",
        "price": 31.3
      }
    ]
  },
  "bleach ed": {
    "current": 23.51,
    "history": [
      {
        "date": "2026-06-24 07:04:13",
        "price": 23.51
      }
    ]
  },
  "greatest hits": {
    "current": 25.92,
    "history": [
      {
        "date": "2026-06-24 06:53:38",
        "price": 25.92
      }
    ]
  },
  "dynamite": {
    "current": 32.67,
    "history": [
      {
        "date": "2026-06-24 06:53:38",
        "price": 32.67
      }
    ]
  },
  "a funk odyssey": {
    "current": 33.99,
    "history": [
      {
        "date": "2026-06-24 06:43:29",
        "price": 33.99
      }
    ]
  },
  "emergency on planet earth": {
    "current": 40.99,
    "history": [
      {
        "date": "2026-06-24 06:53:38",
        "price": 40.99
      }
    ]
  },
  "yield": {
    "current": 23.99,
    "history": [
      {
        "date": "2026-06-24 06:14:10",
        "price": 23.99
      }
    ]
  },
  "playing the angel": {
    "current": 25.99,
    "history": [
      {
        "date": "2026-06-24 06:24:24",
        "price": 25.99
      }
    ]
  },
  "reggatta de blanc": {
    "current": 36.7,
    "history": [
      {
        "date": "2026-06-24 07:04:13",
        "price": 36.7
      }
    ]
  },
  "tici canzoni urgenti": {
    "current": 32.9,
    "history": [
      {
        "date": "2026-06-24 06:53:38",
        "price": 32.9
      }
    ]
  },
  "top": {
    "current": 29.9,
    "history": [
      {
        "date": "2026-06-24 06:53:38",
        "price": 29.9
      }
    ]
  },
  "money for nothing": {
    "current": 32.67,
    "history": [
      {
        "date": "2026-06-24 06:53:38",
        "price": 32.67
      }
    ]
  },
  "the beautiful people toronto broadcast 1998 more double vinyl": {
    "current": 35.0,
    "history": [
      {
        "date": "2026-06-24 06:43:29",
        "price": 35.0
      }
    ]
  },
  "marauder": {
    "current": 28.42,
    "history": [
      {
        "date": "2026-06-24 06:43:29",
        "price": 28.42
      }
    ]
  },
  "vol 3 the subliminal verses violet": {
    "current": 48.97,
    "history": [
      {
        "date": "2026-06-24 07:04:13",
        "price": 48.97
      }
    ]
  },
  "star": {
    "current": 246.63,
    "history": [
      {
        "date": "2026-06-24 07:04:13",
        "price": 246.63
      }
    ]
  },
  "out of time": {
    "current": 21.56,
    "history": [
      {
        "date": "2026-06-24 07:04:13",
        "price": 21.56
      }
    ]
  },
  "noctourniquet": {
    "current": 37.37,
    "history": [
      {
        "date": "2026-06-24 06:34:32",
        "price": 37.37
      }
    ]
  },
  "sleeping with ghosts": {
    "current": 24.5,
    "history": [
      {
        "date": "2026-06-24 07:04:13",
        "price": 24.5
      }
    ]
  },
  "led zeppelin iv": {
    "current": 25.9,
    "history": [
      {
        "date": "2026-06-24 06:34:32",
        "price": 25.9
      }
    ]
  },
  "reload": {
    "current": 49.19,
    "history": [
      {
        "date": "2026-06-24 02:47:41",
        "price": 49.19
      }
    ]
  },
  "s m": {
    "current": 49.52,
    "history": [
      {
        "date": "2026-06-24 07:04:13",
        "price": 49.52
      }
    ]
  },
  "kill em all": {
    "current": 34.12,
    "history": [
      {
        "date": "2026-06-24 07:04:13",
        "price": 34.12
      }
    ]
  },
  "and justice for all": {
    "current": 49.19,
    "history": [
      {
        "date": "2026-06-24 07:04:13",
        "price": 49.19
      }
    ]
  },
  "master of puppets": {
    "current": 30.51,
    "history": [
      {
        "date": "2026-06-24 06:24:24",
        "price": 30.51
      }
    ]
  },
  "back in": {
    "current": 23.85,
    "history": [
      {
        "date": "2026-06-24 07:04:13",
        "price": 23.85
      }
    ]
  },
  "anime salve": {
    "current": 28.97,
    "history": [
      {
        "date": "2026-06-24 06:14:10",
        "price": 28.97
      }
    ]
  },
  "fabrizio de andre": {
    "current": 28.97,
    "history": [
      {
        "date": "2026-06-24 06:53:38",
        "price": 28.97
      }
    ]
  },
  "the beatles": {
    "current": 52.95,
    "history": [
      {
        "date": "2026-06-24 06:24:24",
        "price": 52.95
      }
    ]
  },
  "abbey road": {
    "current": 25.42,
    "history": [
      {
        "date": "2026-06-24 07:04:13",
        "price": 25.42
      }
    ]
  },
  "let love in": {
    "current": 28.99,
    "history": [
      {
        "date": "2026-06-24 06:34:32",
        "price": 28.99
      }
    ]
  },
  "camera a sud": {
    "current": 33.21,
    "history": [
      {
        "date": "2026-06-24 07:04:13",
        "price": 33.21
      }
    ]
  },
  "soft parade": {
    "current": 40.05,
    "history": [
      {
        "date": "2026-06-24 07:04:13",
        "price": 40.05
      }
    ]
  },
  "morrison hotel": {
    "current": 34.25,
    "history": [
      {
        "date": "2026-06-24 07:04:13",
        "price": 34.25
      }
    ]
  },
  "substance": {
    "current": 36.8,
    "history": [
      {
        "date": "2026-06-24 07:04:13",
        "price": 36.8
      }
    ]
  },
  "heroes": {
    "current": 31.99,
    "history": [
      {
        "date": "2026-06-24 06:53:38",
        "price": 31.99
      }
    ]
  }
}