{
  "innerspeaker": {
    "current": 26.9,
    "history": [
      {
        "date": "2026-06-21",
        "price": 56.9
      },
      {
        "date": "2026-06-21",
        "price": 26.9
      }
    ]
  },
  "viva hate hq ltd download": {
    "current": 26.99,
    "history": [
      {
        "date": "2026-06-21",
        "price": 26.99
      }
    ]
  },
  "boarding house reach": {
    "current": 35.97,
    "history": [
      {
        "date": "2026-06-21",
        "price": 35.97
      }
    ]
  },
  "fear of the dawn": {
    "current": 29.3,
    "history": [
      {
        "date": "2026-06-21",
        "price": 29.3
      }
    ]
  },
  "mainstream": {
    "current": 33.21,
    "history": [
      {
        "date": "2026-06-21",
        "price": 33.21
      }
    ]
  },
  "evergreen e altre canzoni": {
    "current": 33.21,
    "history": [
      {
        "date": "2026-06-21",
        "price": 33.21
      }
    ]
  },
  "resta vile maschio dove vai": {
    "current": 38.0,
    "history": [
      {
        "date": "2026-06-21",
        "price": 38.0
      }
    ]
  },
  "songs of a lost world": {
    "current": 31.9,
    "history": [
      {
        "date": "2026-06-21",
        "price": 31.9
      }
    ]
  },
  "un du": {
    "current": 53.91,
    "history": [
      {
        "date": "2026-06-21",
        "price": 53.91
      }
    ]
  },
  "hot fuzz": {
    "current": 32.8,
    "history": [
      {
        "date": "2026-06-21",
        "price": 32.8
      }
    ]
  },
  "fear of music": {
    "current": 34.89,
    "history": [
      {
        "date": "2026-06-21",
        "price": 34.89
      }
    ]
  },
  "naked": {
    "current": 35.9,
    "history": [
      {
        "date": "2026-06-21",
        "price": 35.9
      }
    ]
  },
  "remain in light": {
    "current": 25.9,
    "history": [
      {
        "date": "2026-06-21",
        "price": 25.9
      }
    ]
  },
  "follow the leader": {
    "current": 23.99,
    "history": [
      {
        "date": "2026-06-21",
        "price": 23.99
      }
    ]
  },
  "new adventures in hi fi": {
    "current": 45.9,
    "history": [
      {
        "date": "2026-06-21",
        "price": 45.9
      }
    ]
  },
  "bleach ed": {
    "current": 25.99,
    "history": [
      {
        "date": "2026-06-21",
        "price": 25.99
      }
    ]
  },
  "synkronized": {
    "current": 23.99,
    "history": [
      {
        "date": "2026-06-21",
        "price": 23.99
      }
    ]
  },
  "yield": {
    "current": 23.99,
    "history": [
      {
        "date": "2026-06-21",
        "price": 23.99
      }
    ]
  },
  "playing the angel": {
    "current": 25.99,
    "history": [
      {
        "date": "2026-06-21",
        "price": 25.99
      }
    ]
  },
  "la matematica dei rami": {
    "current": 33.31,
    "history": [
      {
        "date": "2026-06-21",
        "price": 33.31
      }
    ]
  },
  "top": {
    "current": 29.9,
    "history": [
      {
        "date": "2026-06-21",
        "price": 29.9
      }
    ]
  },
  "hatful of hollow": {
    "current": 25.9,
    "history": [
      {
        "date": "2026-06-21",
        "price": 25.9
      }
    ]
  },
  "the queen is dead": {
    "current": 24.9,
    "history": [
      {
        "date": "2026-06-21",
        "price": 24.9
      }
    ]
  },
  "ixnay on the hombre": {
    "current": 32.23,
    "history": [
      {
        "date": "2026-06-21",
        "price": 32.23
      }
    ]
  },
  "money for nothing": {
    "current": 38.43,
    "history": [
      {
        "date": "2026-06-21",
        "price": 38.43
      }
    ]
  },
  "good bye lenin": {
    "current": 30.86,
    "history": [
      {
        "date": "2026-06-21",
        "price": 30.86
      }
    ]
  },
  "the beautiful people toronto broadcast 1998 more double vinyl": {
    "current": 35.0,
    "history": [
      {
        "date": "2026-06-21",
        "price": 35.0
      }
    ]
  },
  "marauder": {
    "current": 28.42,
    "history": [
      {
        "date": "2026-06-21",
        "price": 28.42
      }
    ]
  },
  "star": {
    "current": 246.63,
    "history": [
      {
        "date": "2026-06-21",
        "price": 246.63
      }
    ]
  },
  "noctourniquet": {
    "current": 37.37,
    "history": [
      {
        "date": "2026-06-21",
        "price": 37.37
      }
    ]
  },
  "metallica": {
    "current": 35.95,
    "history": [
      {
        "date": "2026-06-21",
        "price": 35.95
      }
    ]
  },
  "led zeppelin iii": {
    "current": 26.95,
    "history": [
      {
        "date": "2026-06-21",
        "price": 26.95
      }
    ]
  },
  "reload": {
    "current": 49.19,
    "history": [
      {
        "date": "2026-06-21",
        "price": 49.19
      }
    ]
  },
  "s m": {
    "current": 49.8,
    "history": [
      {
        "date": "2026-06-21",
        "price": 49.8
      }
    ]
  },
  "kill em all": {
    "current": 36.99,
    "history": [
      {
        "date": "2026-06-21",
        "price": 36.99
      }
    ]
  },
  "and justice for all": {
    "current": 49.19,
    "history": [
      {
        "date": "2026-06-21",
        "price": 49.19
      }
    ]
  },
  "appetite for destruction": {
    "current": 29.9,
    "history": [
      {
        "date": "2026-06-21",
        "price": 29.9
      }
    ]
  },
  "back in": {
    "current": 23.85,
    "history": [
      {
        "date": "2026-06-21",
        "price": 23.85
      }
    ]
  },
  "ultinate": {
    "current": 37.42,
    "history": [
      {
        "date": "2026-06-21",
        "price": 37.42
      }
    ]
  },
  "the beatles": {
    "current": 52.95,
    "history": [
      {
        "date": "2026-06-21",
        "price": 52.95
      }
    ]
  },
  "1": {
    "current": 51.8,
    "history": [
      {
        "date": "2026-06-21",
        "price": 51.8
      }
    ]
  },
  "abbey road": {
    "current": 29.9,
    "history": [
      {
        "date": "2026-06-21",
        "price": 29.9
      }
    ]
  },
  "let love in": {
    "current": 28.99,
    "history": [
      {
        "date": "2026-06-21",
        "price": 28.99
      }
    ]
  },
  "morrison hotel": {
    "current": 34.73,
    "history": [
      {
        "date": "2026-06-21",
        "price": 34.73
      }
    ]
  },
  "heroes": {
    "current": 31.99,
    "history": [
      {
        "date": "2026-06-21",
        "price": 31.99
      }
    ]
  },
  "the rise and fall of ziggy stardust": {
    "current": 28.9,
    "history": [
      {
        "date": "2026-06-21",
        "price": 28.9
      }
    ]
  }
}